[
 {
  "table":"SPROXDAT",
  "data":
  [
   {
    "OBJECT":"TABL",
    "OBJ_NAME":"ZJOURNAL_ENTRY_CREATE_REQUES17",
    "OBJECT1":"FIEL",
    "OBJ_NAME1":"CASH_DISCOUNT1DAYS",
    "OBJECT2":"FIEL",
    "OBJ_NAME2":"CASH_DISCOUNT1DAYS",
    "INACTIVE":"",
    "OBJECT_R":"DTEL",
    "OBJ_NAME_R":"ZDAY_DURATION",
    "ID":"<element> CashDiscount1Days <type> JournalEntryCreateRequestJournalEntryCashDiscountTerms http://sap.com/xi/SAPSCORE/SFIN http://sap.com/xi/SAPSCORE/SFIN",
    "IFR_TYPE":"element",
    "IFR_NAME":"CashDiscount1Days",
    "IFR_TEXT":"",
    "IFR_LANGU":"",
    "IFR_REPTERM":"",
    "IFR_LABEL_F":"",
    "IFR_LABEL_C":"",
    "IFR_TEXTID":"",
    "IFR_TAGTYP":"E",
    "IFR_MINOCC":0,
    "IFR_MAXOCC":1,
    "IFR_OPTNL":"X",
    "IFR_DEFLT":"",
    "IFR_QUALIF":"",
    "IFR_XSDTYP":"",
    "IFR_LENGTH":0,
    "IFR_MAXLEN":0,
    "IFR_MINLEN":0,
    "IFR_NILLABLE":"",
    "IFR_PATTRN":"",
    "IFR_PREC":0,
    "IFR_SCALE":-2,
    "IFR_FAULT":"",
    "IFR_ACTIONCODE":"",
    "IFR_IDEMPOTENT":"",
    "R3_TYPE":"FIEL",
    "R3_NAME":"CASH_DISCOUNT1DAYS",
    "R3_TEXT":"",
    "R3_DATATYP":"",
    "R3_LENGTH":0,
    "R3_DECIMAL":0,
    "R3_REFTO":"",
    "R3_DTREF":"",
    "R3_INCLUDE":"",
    "R3_SEQNUM":3,
    "R3_BOXED":"",
    "CATEGORY":"",
    "DIRECTION":"",
    "INSTANCE":"",
    "SYNCHRON":"",
    "KEYPARAM":"",
    "PROBLEMS":"",
    "WARNINGS":"",
    "PROBL_INF":"",
    "FURTHERDATA":"",
    "ENUMTYPE":""
   },
   {
    "OBJECT":"TABL",
    "OBJ_NAME":"ZJOURNAL_ENTRY_CREATE_REQUES17",
    "OBJECT1":"FIEL",
    "OBJ_NAME1":"CASH_DISCOUNT1PERCENT",
    "OBJECT2":"FIEL",
    "OBJ_NAME2":"CASH_DISCOUNT1PERCENT",
    "INACTIVE":"",
    "OBJECT_R":"DTEL",
    "OBJ_NAME_R":"ZPERCENT1",
    "ID":"<element> CashDiscount1Percent <type> JournalEntryCreateRequestJournalEntryCashDiscountTerms http://sap.com/xi/SAPSCORE/SFIN http://sap.com/xi/SAPSCORE/SFIN",
    "IFR_TYPE":"element",
    "IFR_NAME":"CashDiscount1Percent",
    "IFR_TEXT":"",
    "IFR_LANGU":"",
    "IFR_REPTERM":"",
    "IFR_LABEL_F":"",
    "IFR_LABEL_C":"",
    "IFR_TEXTID":"",
    "IFR_TAGTYP":"E",
    "IFR_MINOCC":0,
    "IFR_MAXOCC":1,
    "IFR_OPTNL":"X",
    "IFR_DEFLT":"",
    "IFR_QUALIF":"",
    "IFR_XSDTYP":"",
    "IFR_LENGTH":0,
    "IFR_MAXLEN":0,
    "IFR_MINLEN":0,
    "IFR_NILLABLE":"",
    "IFR_PATTRN":"",
    "IFR_PREC":0,
    "IFR_SCALE":-2,
    "IFR_FAULT":"",
    "IFR_ACTIONCODE":"",
    "IFR_IDEMPOTENT":"",
    "R3_TYPE":"FIEL",
    "R3_NAME":"CASH_DISCOUNT1PERCENT",
    "R3_TEXT":"",
    "R3_DATATYP":"",
    "R3_LENGTH":0,
    "R3_DECIMAL":0,
    "R3_REFTO":"",
    "R3_DTREF":"",
    "R3_INCLUDE":"",
    "R3_SEQNUM":4,
    "R3_BOXED":"",
    "CATEGORY":"",
    "DIRECTION":"",
    "INSTANCE":"",
    "SYNCHRON":"",
    "KEYPARAM":"",
    "PROBLEMS":"",
    "WARNINGS":"",
    "PROBL_INF":"",
    "FURTHERDATA":"",
    "ENUMTYPE":""
   },
   {
    "OBJECT":"TABL",
    "OBJ_NAME":"ZJOURNAL_ENTRY_CREATE_REQUES17",
    "OBJECT1":"FIEL",
    "OBJ_NAME1":"CASH_DISCOUNT2DAYS",
    "OBJECT2":"FIEL",
    "OBJ_NAME2":"CASH_DISCOUNT2DAYS",
    "INACTIVE":"",
    "OBJECT_R":"DTEL",
    "OBJ_NAME_R":"ZDAY_DURATION",
    "ID":"<element> CashDiscount2Days <type> JournalEntryCreateRequestJournalEntryCashDiscountTerms http://sap.com/xi/SAPSCORE/SFIN http://sap.com/xi/SAPSCORE/SFIN",
    "IFR_TYPE":"element",
    "IFR_NAME":"CashDiscount2Days",
    "IFR_TEXT":"",
    "IFR_LANGU":"",
    "IFR_REPTERM":"",
    "IFR_LABEL_F":"",
    "IFR_LABEL_C":"",
    "IFR_TEXTID":"",
    "IFR_TAGTYP":"E",
    "IFR_MINOCC":0,
    "IFR_MAXOCC":1,
    "IFR_OPTNL":"X",
    "IFR_DEFLT":"",
    "IFR_QUALIF":"",
    "IFR_XSDTYP":"",
    "IFR_LENGTH":0,
    "IFR_MAXLEN":0,
    "IFR_MINLEN":0,
    "IFR_NILLABLE":"",
    "IFR_PATTRN":"",
    "IFR_PREC":0,
    "IFR_SCALE":-2,
    "IFR_FAULT":"",
    "IFR_ACTIONCODE":"",
    "IFR_IDEMPOTENT":"",
    "R3_TYPE":"FIEL",
    "R3_NAME":"CASH_DISCOUNT2DAYS",
    "R3_TEXT":"",
    "R3_DATATYP":"",
    "R3_LENGTH":0,
    "R3_DECIMAL":0,
    "R3_REFTO":"",
    "R3_DTREF":"",
    "R3_INCLUDE":"",
    "R3_SEQNUM":5,
    "R3_BOXED":"",
    "CATEGORY":"",
    "DIRECTION":"",
    "INSTANCE":"",
    "SYNCHRON":"",
    "KEYPARAM":"",
    "PROBLEMS":"",
    "WARNINGS":"",
    "PROBL_INF":"",
    "FURTHERDATA":"",
    "ENUMTYPE":""
   },
   {
    "OBJECT":"TABL",
    "OBJ_NAME":"ZJOURNAL_ENTRY_CREATE_REQUES17",
    "OBJECT1":"FIEL",
    "OBJ_NAME1":"CASH_DISCOUNT2PERCENT",
    "OBJECT2":"FIEL",
    "OBJ_NAME2":"CASH_DISCOUNT2PERCENT",
    "INACTIVE":"",
    "OBJECT_R":"DTEL",
    "OBJ_NAME_R":"ZPERCENT1",
    "ID":"<element> CashDiscount2Percent <type> JournalEntryCreateRequestJournalEntryCashDiscountTerms http://sap.com/xi/SAPSCORE/SFIN http://sap.com/xi/SAPSCORE/SFIN",
    "IFR_TYPE":"element",
    "IFR_NAME":"CashDiscount2Percent",
    "IFR_TEXT":"",
    "IFR_LANGU":"",
    "IFR_REPTERM":"",
    "IFR_LABEL_F":"",
    "IFR_LABEL_C":"",
    "IFR_TEXTID":"",
    "IFR_TAGTYP":"E",
    "IFR_MINOCC":0,
    "IFR_MAXOCC":1,
    "IFR_OPTNL":"X",
    "IFR_DEFLT":"",
    "IFR_QUALIF":"",
    "IFR_XSDTYP":"",
    "IFR_LENGTH":0,
    "IFR_MAXLEN":0,
    "IFR_MINLEN":0,
    "IFR_NILLABLE":"",
    "IFR_PATTRN":"",
    "IFR_PREC":0,
    "IFR_SCALE":-2,
    "IFR_FAULT":"",
    "IFR_ACTIONCODE":"",
    "IFR_IDEMPOTENT":"",
    "R3_TYPE":"FIEL",
    "R3_NAME":"CASH_DISCOUNT2PERCENT",
    "R3_TEXT":"",
    "R3_DATATYP":"",
    "R3_LENGTH":0,
    "R3_DECIMAL":0,
    "R3_REFTO":"",
    "R3_DTREF":"",
    "R3_INCLUDE":"",
    "R3_SEQNUM":6,
    "R3_BOXED":"",
    "CATEGORY":"",
    "DIRECTION":"",
    "INSTANCE":"",
    "SYNCHRON":"",
    "KEYPARAM":"",
    "PROBLEMS":"",
    "WARNINGS":"",
    "PROBL_INF":"",
    "FURTHERDATA":"",
    "ENUMTYPE":""
   },
   {
    "OBJECT":"TABL",
    "OBJ_NAME":"ZJOURNAL_ENTRY_CREATE_REQUES17",
    "OBJECT1":"FIEL",
    "OBJ_NAME1":"CASH_DISCOUNT_BASE_AMOUNT",
    "OBJECT2":"FIEL",
    "OBJ_NAME2":"CASH_DISCOUNT_BASE_AMOUNT",
    "INACTIVE":"",
    "OBJECT_R":"TABL",
    "OBJ_NAME_R":"ZAMOUNT",
    "ID":"<element> CashDiscountBaseAmount <type> JournalEntryCreateRequestJournalEntryCashDiscountTerms http://sap.com/xi/SAPSCORE/SFIN http://sap.com/xi/SAPSCORE/SFIN",
    "IFR_TYPE":"element",
    "IFR_NAME":"CashDiscountBaseAmount",
    "IFR_TEXT":"",
    "IFR_LANGU":"",
    "IFR_REPTERM":"",
    "IFR_LABEL_F":"",
    "IFR_LABEL_C":"",
    "IFR_TEXTID":"",
    "IFR_TAGTYP":"E",
    "IFR_MINOCC":0,
    "IFR_MAXOCC":1,
    "IFR_OPTNL":"X",
    "IFR_DEFLT":"",
    "IFR_QUALIF":"",
    "IFR_XSDTYP":"",
    "IFR_LENGTH":0,
    "IFR_MAXLEN":0,
    "IFR_MINLEN":0,
    "IFR_NILLABLE":"",
    "IFR_PATTRN":"",
    "IFR_PREC":0,
    "IFR_SCALE":-2,
    "IFR_FAULT":"",
    "IFR_ACTIONCODE":"",
    "IFR_IDEMPOTENT":"",
    "R3_TYPE":"FIEL",
    "R3_NAME":"CASH_DISCOUNT_BASE_AMOUNT",
    "R3_TEXT":"",
    "R3_DATATYP":"",
    "R3_LENGTH":0,
    "R3_DECIMAL":0,
    "R3_REFTO":"",
    "R3_DTREF":"",
    "R3_INCLUDE":"",
    "R3_SEQNUM":1,
    "R3_BOXED":"",
    "CATEGORY":"",
    "DIRECTION":"",
    "INSTANCE":"",
    "SYNCHRON":"",
    "KEYPARAM":"",
    "PROBLEMS":"",
    "WARNINGS":"",
    "PROBL_INF":"",
    "FURTHERDATA":"",
    "ENUMTYPE":""
   },
   {
    "OBJECT":"TABL",
    "OBJ_NAME":"ZJOURNAL_ENTRY_CREATE_REQUES17",
    "OBJECT1":"FIEL",
    "OBJ_NAME1":"DUE_CALCULATION_BASE_DATE",
    "OBJECT2":"FIEL",
    "OBJ_NAME2":"DUE_CALCULATION_BASE_DATE",
    "INACTIVE":"",
    "OBJECT_R":"DTEL",
    "OBJ_NAME_R":"ZDATE2",
    "ID":"<element> DueCalculationBaseDate <type> JournalEntryCreateRequestJournalEntryCashDiscountTerms http://sap.com/xi/SAPSCORE/SFIN http://sap.com/xi/SAPSCORE/SFIN",
    "IFR_TYPE":"element",
    "IFR_NAME":"DueCalculationBaseDate",
    "IFR_TEXT":"",
    "IFR_LANGU":"",
    "IFR_REPTERM":"",
    "IFR_LABEL_F":"",
    "IFR_LABEL_C":"",
    "IFR_TEXTID":"",
    "IFR_TAGTYP":"E",
    "IFR_MINOCC":1,
    "IFR_MAXOCC":1,
    "IFR_OPTNL":"",
    "IFR_DEFLT":"",
    "IFR_QUALIF":"",
    "IFR_XSDTYP":"",
    "IFR_LENGTH":0,
    "IFR_MAXLEN":0,
    "IFR_MINLEN":0,
    "IFR_NILLABLE":"",
    "IFR_PATTRN":"",
    "IFR_PREC":0,
    "IFR_SCALE":-2,
    "IFR_FAULT":"",
    "IFR_ACTIONCODE":"",
    "IFR_IDEMPOTENT":"",
    "R3_TYPE":"FIEL",
    "R3_NAME":"DUE_CALCULATION_BASE_DATE",
    "R3_TEXT":"",
    "R3_DATATYP":"",
    "R3_LENGTH":0,
    "R3_DECIMAL":0,
    "R3_REFTO":"",
    "R3_DTREF":"",
    "R3_INCLUDE":"",
    "R3_SEQNUM":2,
    "R3_BOXED":"",
    "CATEGORY":"",
    "DIRECTION":"",
    "INSTANCE":"",
    "SYNCHRON":"",
    "KEYPARAM":"",
    "PROBLEMS":"",
    "WARNINGS":"",
    "PROBL_INF":"",
    "FURTHERDATA":"",
    "ENUMTYPE":""
   },
   {
    "OBJECT":"TABL",
    "OBJ_NAME":"ZJOURNAL_ENTRY_CREATE_REQUES17",
    "OBJECT1":"FIEL",
    "OBJ_NAME1":"NET_PAYMENT_DAYS",
    "OBJECT2":"FIEL",
    "OBJ_NAME2":"NET_PAYMENT_DAYS",
    "INACTIVE":"",
    "OBJECT_R":"DTEL",
    "OBJ_NAME_R":"ZDAY_DURATION",
    "ID":"<element> NetPaymentDays <type> JournalEntryCreateRequestJournalEntryCashDiscountTerms http://sap.com/xi/SAPSCORE/SFIN http://sap.com/xi/SAPSCORE/SFIN",
    "IFR_TYPE":"element",
    "IFR_NAME":"NetPaymentDays",
    "IFR_TEXT":"",
    "IFR_LANGU":"",
    "IFR_REPTERM":"",
    "IFR_LABEL_F":"",
    "IFR_LABEL_C":"",
    "IFR_TEXTID":"",
    "IFR_TAGTYP":"E",
    "IFR_MINOCC":1,
    "IFR_MAXOCC":1,
    "IFR_OPTNL":"",
    "IFR_DEFLT":"",
    "IFR_QUALIF":"",
    "IFR_XSDTYP":"",
    "IFR_LENGTH":0,
    "IFR_MAXLEN":0,
    "IFR_MINLEN":0,
    "IFR_NILLABLE":"",
    "IFR_PATTRN":"",
    "IFR_PREC":0,
    "IFR_SCALE":-2,
    "IFR_FAULT":"",
    "IFR_ACTIONCODE":"",
    "IFR_IDEMPOTENT":"",
    "R3_TYPE":"FIEL",
    "R3_NAME":"NET_PAYMENT_DAYS",
    "R3_TEXT":"",
    "R3_DATATYP":"",
    "R3_LENGTH":0,
    "R3_DECIMAL":0,
    "R3_REFTO":"",
    "R3_DTREF":"",
    "R3_INCLUDE":"",
    "R3_SEQNUM":7,
    "R3_BOXED":"",
    "CATEGORY":"",
    "DIRECTION":"",
    "INSTANCE":"",
    "SYNCHRON":"",
    "KEYPARAM":"",
    "PROBLEMS":"",
    "WARNINGS":"",
    "PROBL_INF":"",
    "FURTHERDATA":"",
    "ENUMTYPE":""
   },
   {
    "OBJECT":"TABL",
    "OBJ_NAME":"ZJOURNAL_ENTRY_CREATE_REQUES17",
    "OBJECT1":"TABL",
    "OBJ_NAME1":"ZJOURNAL_ENTRY_CREATE_REQUES17",
    "OBJECT2":"TABL",
    "OBJ_NAME2":"ZJOURNAL_ENTRY_CREATE_REQUES17",
    "INACTIVE":"",
    "OBJECT_R":"",
    "OBJ_NAME_R":"",
    "ID":"<type> JournalEntryCreateRequestJournalEntryCashDiscountTerms http://sap.com/xi/SAPSCORE/SFIN http://sap.com/xi/SAPSCORE/SFIN",
    "IFR_TYPE":"type",
    "IFR_NAME":"JournalEntryCreateRequestJournalEntryCashDiscountTerms",
    "IFR_TEXT":"",
    "IFR_LANGU":"",
    "IFR_REPTERM":"",
    "IFR_LABEL_F":"",
    "IFR_LABEL_C":"",
    "IFR_TEXTID":"",
    "IFR_TAGTYP":"",
    "IFR_MINOCC":0,
    "IFR_MAXOCC":0,
    "IFR_OPTNL":"",
    "IFR_DEFLT":"",
    "IFR_QUALIF":"",
    "IFR_XSDTYP":"",
    "IFR_LENGTH":0,
    "IFR_MAXLEN":0,
    "IFR_MINLEN":0,
    "IFR_NILLABLE":"",
    "IFR_PATTRN":"",
    "IFR_PREC":0,
    "IFR_SCALE":-2,
    "IFR_FAULT":"",
    "IFR_ACTIONCODE":"",
    "IFR_IDEMPOTENT":"",
    "R3_TYPE":"TABL",
    "R3_NAME":"ZJOURNAL_ENTRY_CREATE_REQUES17",
    "R3_TEXT":"Proxy Structure (generated)",
    "R3_DATATYP":"",
    "R3_LENGTH":0,
    "R3_DECIMAL":0,
    "R3_REFTO":"",
    "R3_DTREF":"",
    "R3_INCLUDE":"",
    "R3_SEQNUM":0,
    "R3_BOXED":"",
    "CATEGORY":"ifmtypedef",
    "DIRECTION":"",
    "INSTANCE":"",
    "SYNCHRON":"",
    "KEYPARAM":"",
    "PROBLEMS":"",
    "WARNINGS":"",
    "PROBL_INF":"",
    "FURTHERDATA":"",
    "ENUMTYPE":""
   }
  ]
 },
 {
  "table":"SPROXHDR",
  "data":
  [
   {
    "OBJECT":"TABL",
    "OBJ_NAME":"ZJOURNAL_ENTRY_CREATE_REQUES17",
    "INACTIVE":"",
    "OBJECT_M":"TABL",
    "OBJ_NAME_M":"ZJOURNAL_ENTRY_CREATE_REQUES17",
    "HASH_ID":"D8270DDE02909F9130D383064E211C70B6481AC7",
    "ID":"<type> JournalEntryCreateRequestJournalEntryCashDiscountTerms http://sap.com/xi/SAPSCORE/SFIN http://sap.com/xi/SAPSCORE/SFIN",
    "IFR_GLOBAL":"X",
    "IFR_TYPE":"type",
    "IFR_NAME":"JournalEntryCreateRequestJournalEntryCashDiscountTerms",
    "IFR_NSPCE":"http://sap.com/xi/SAPSCORE/SFIN",
    "IFR_GNSPCE":"http://sap.com/xi/SAPSCORE/SFIN",
    "CREATED_ON":"+020251204031722",
    "CREATED_BY":"SAP_CUSTOMER",
    "CHANGED_ON":"+020251204032528",
    "CHANGED_BY":"SAP_CUSTOMER",
    "GEN_VERS":5,
    "PREFIX":"",
    "CATEGORY":"ifmtypedef",
    "DIRECTION":"",
    "SYNCHRON":"",
    "GEN_APPL":"WEBSERVICES",
    "ENH_NAME":"",
    "ENH_NSPCE":"",
    "ENH_HASH_ID":"",
    "XML_NSPCE":"http://sap.com/xi/SAPSCORE/SFIN",
    "XML_NAME":"JournalEntryCreateRequestJournalEntryCashDiscountTerms",
    "FURTHER_DATA":"",
    "BO_DATA":"",
    "CHANGED_ON_IFR":"0",
    "VERSION_ID":"",
    "IFR_STATE":"",
    "EVENT":"",
    "DYNAMIC":"",
    "STCM":"",
    "ABAP_LANGUAGE_VERSION":"5"
   }
  ]
 },
 {
  "table":"TADIR",
  "data":
  [
   {
    "PGMID":"R3TR",
    "OBJECT":"SPRX",
    "OBJ_NAME":"TABLZJOURNAL_ENTRY_CREATE_REQUES17",
    "KORRNUM":"",
    "SRCSYSTEM":"...",
    "AUTHOR":"SAP_CUSTOMER",
    "SRCDEP":"",
    "DEVCLASS":"ZETR_EXPORT_JE",
    "GENFLAG":"",
    "EDTFLAG":"",
    "CPROJECT":" L",
    "MASTERLANG":"E",
    "VERSID":"",
    "PAKNOCHECK":"",
    "OBJSTABLTY":"",
    "COMPONENT":"",
    "CRELEASE":"",
    "DELFLAG":"",
    "TRANSLTTXT":"",
    "CREATED_ON":"2025-12-04",
    "CHECK_DATE":"2025-12-04",
    "CHECK_CFG":""
   }
  ]
 }
]