[
 {
  "table":"SPROXDAT",
  "data":
  [
   {
    "OBJECT":"TABL",
    "OBJ_NAME":"ZBUSINESS_DOCUMENT_MESSAGE_HE3",
    "OBJECT1":"FIEL",
    "OBJ_NAME1":"BUSINESS_SCOPE",
    "OBJECT2":"FIEL",
    "OBJ_NAME2":"BUSINESS_SCOPE",
    "INACTIVE":"",
    "OBJECT_R":"TTYP",
    "OBJ_NAME_R":"ZBUSINESS_SCOPE_TAB1",
    "ID":"<element> BusinessScope <type> BusinessDocumentMessageHeader http://sap.com/xi/SD-BIL/Global2 http://sap.com/xi/SD-BIL/Global2",
    "IFR_TYPE":"element",
    "IFR_NAME":"BusinessScope",
    "IFR_TEXT":"",
    "IFR_LANGU":"",
    "IFR_REPTERM":"",
    "IFR_LABEL_F":"",
    "IFR_LABEL_C":"",
    "IFR_TEXTID":"",
    "IFR_TAGTYP":"L",
    "IFR_MINOCC":0,
    "IFR_MAXOCC":65535,
    "IFR_OPTNL":"X",
    "IFR_DEFLT":"",
    "IFR_QUALIF":"",
    "IFR_XSDTYP":"",
    "IFR_LENGTH":0,
    "IFR_MAXLEN":0,
    "IFR_MINLEN":0,
    "IFR_NILLABLE":"",
    "IFR_PATTRN":"",
    "IFR_PREC":0,
    "IFR_SCALE":-2,
    "IFR_FAULT":"",
    "IFR_ACTIONCODE":"",
    "IFR_IDEMPOTENT":"",
    "R3_TYPE":"FIEL",
    "R3_NAME":"BUSINESS_SCOPE",
    "R3_TEXT":"",
    "R3_DATATYP":"",
    "R3_LENGTH":0,
    "R3_DECIMAL":0,
    "R3_REFTO":"",
    "R3_DTREF":"",
    "R3_INCLUDE":"",
    "R3_SEQNUM":9,
    "R3_BOXED":"",
    "CATEGORY":"",
    "DIRECTION":"",
    "INSTANCE":"",
    "SYNCHRON":"",
    "KEYPARAM":"",
    "PROBLEMS":"",
    "WARNINGS":"",
    "PROBL_INF":"",
    "FURTHERDATA":"",
    "ENUMTYPE":""
   },
   {
    "OBJECT":"TABL",
    "OBJ_NAME":"ZBUSINESS_DOCUMENT_MESSAGE_HE3",
    "OBJECT1":"FIEL",
    "OBJ_NAME1":"CREATION_DATE_TIME",
    "OBJECT2":"FIEL",
    "OBJ_NAME2":"CREATION_DATE_TIME",
    "INACTIVE":"",
    "OBJECT_R":"DTEL",
    "OBJ_NAME_R":"ZGLOBAL_DATE_TIME1",
    "ID":"<element> CreationDateTime <type> BusinessDocumentMessageHeader http://sap.com/xi/SD-BIL/Global2 http://sap.com/xi/SD-BIL/Global2",
    "IFR_TYPE":"element",
    "IFR_NAME":"CreationDateTime",
    "IFR_TEXT":"",
    "IFR_LANGU":"",
    "IFR_REPTERM":"",
    "IFR_LABEL_F":"",
    "IFR_LABEL_C":"",
    "IFR_TEXTID":"",
    "IFR_TAGTYP":"E",
    "IFR_MINOCC":1,
    "IFR_MAXOCC":1,
    "IFR_OPTNL":"",
    "IFR_DEFLT":"",
    "IFR_QUALIF":"",
    "IFR_XSDTYP":"",
    "IFR_LENGTH":0,
    "IFR_MAXLEN":0,
    "IFR_MINLEN":0,
    "IFR_NILLABLE":"",
    "IFR_PATTRN":"",
    "IFR_PREC":0,
    "IFR_SCALE":-2,
    "IFR_FAULT":"",
    "IFR_ACTIONCODE":"",
    "IFR_IDEMPOTENT":"",
    "R3_TYPE":"FIEL",
    "R3_NAME":"CREATION_DATE_TIME",
    "R3_TEXT":"",
    "R3_DATATYP":"",
    "R3_LENGTH":0,
    "R3_DECIMAL":0,
    "R3_REFTO":"",
    "R3_DTREF":"",
    "R3_INCLUDE":"",
    "R3_SEQNUM":3,
    "R3_BOXED":"",
    "CATEGORY":"",
    "DIRECTION":"",
    "INSTANCE":"",
    "SYNCHRON":"",
    "KEYPARAM":"",
    "PROBLEMS":"",
    "WARNINGS":"",
    "PROBL_INF":"",
    "FURTHERDATA":"",
    "ENUMTYPE":""
   },
   {
    "OBJECT":"TABL",
    "OBJ_NAME":"ZBUSINESS_DOCUMENT_MESSAGE_HE3",
    "OBJECT1":"FIEL",
    "OBJ_NAME1":"ID",
    "OBJECT2":"FIEL",
    "OBJ_NAME2":"ID",
    "INACTIVE":"",
    "OBJECT_R":"TABL",
    "OBJ_NAME_R":"ZBUSINESS_DOCUMENT_MESSAGE_ID2",
    "ID":"<element> ID <type> BusinessDocumentMessageHeader http://sap.com/xi/SD-BIL/Global2 http://sap.com/xi/SD-BIL/Global2",
    "IFR_TYPE":"element",
    "IFR_NAME":"ID",
    "IFR_TEXT":"",
    "IFR_LANGU":"",
    "IFR_REPTERM":"",
    "IFR_LABEL_F":"",
    "IFR_LABEL_C":"",
    "IFR_TEXTID":"",
    "IFR_TAGTYP":"E",
    "IFR_MINOCC":0,
    "IFR_MAXOCC":1,
    "IFR_OPTNL":"X",
    "IFR_DEFLT":"",
    "IFR_QUALIF":"",
    "IFR_XSDTYP":"",
    "IFR_LENGTH":0,
    "IFR_MAXLEN":0,
    "IFR_MINLEN":0,
    "IFR_NILLABLE":"",
    "IFR_PATTRN":"",
    "IFR_PREC":0,
    "IFR_SCALE":-2,
    "IFR_FAULT":"",
    "IFR_ACTIONCODE":"",
    "IFR_IDEMPOTENT":"",
    "R3_TYPE":"FIEL",
    "R3_NAME":"ID",
    "R3_TEXT":"",
    "R3_DATATYP":"",
    "R3_LENGTH":0,
    "R3_DECIMAL":0,
    "R3_REFTO":"",
    "R3_DTREF":"",
    "R3_INCLUDE":"",
    "R3_SEQNUM":1,
    "R3_BOXED":"",
    "CATEGORY":"",
    "DIRECTION":"",
    "INSTANCE":"",
    "SYNCHRON":"",
    "KEYPARAM":"",
    "PROBLEMS":"",
    "WARNINGS":"",
    "PROBL_INF":"",
    "FURTHERDATA":"",
    "ENUMTYPE":""
   },
   {
    "OBJECT":"TABL",
    "OBJ_NAME":"ZBUSINESS_DOCUMENT_MESSAGE_HE3",
    "OBJECT1":"FIEL",
    "OBJ_NAME1":"RECIPIENT_BUSINESS_SYSTEM_ID",
    "OBJECT2":"FIEL",
    "OBJ_NAME2":"RECIPIENT_BUSINESS_SYSTEM_ID",
    "INACTIVE":"",
    "OBJECT_R":"DTEL",
    "OBJ_NAME_R":"ZBUSINESS_SYSTEM_ID1",
    "ID":"<element> RecipientBusinessSystemID <type> BusinessDocumentMessageHeader http://sap.com/xi/SD-BIL/Global2 http://sap.com/xi/SD-BIL/Global2",
    "IFR_TYPE":"element",
    "IFR_NAME":"RecipientBusinessSystemID",
    "IFR_TEXT":"",
    "IFR_LANGU":"",
    "IFR_REPTERM":"",
    "IFR_LABEL_F":"",
    "IFR_LABEL_C":"",
    "IFR_TEXTID":"",
    "IFR_TAGTYP":"E",
    "IFR_MINOCC":0,
    "IFR_MAXOCC":1,
    "IFR_OPTNL":"X",
    "IFR_DEFLT":"",
    "IFR_QUALIF":"",
    "IFR_XSDTYP":"",
    "IFR_LENGTH":0,
    "IFR_MAXLEN":0,
    "IFR_MINLEN":0,
    "IFR_NILLABLE":"",
    "IFR_PATTRN":"",
    "IFR_PREC":0,
    "IFR_SCALE":-2,
    "IFR_FAULT":"",
    "IFR_ACTIONCODE":"",
    "IFR_IDEMPOTENT":"",
    "R3_TYPE":"FIEL",
    "R3_NAME":"RECIPIENT_BUSINESS_SYSTEM_ID",
    "R3_TEXT":"",
    "R3_DATATYP":"",
    "R3_LENGTH":0,
    "R3_DECIMAL":0,
    "R3_REFTO":"",
    "R3_DTREF":"",
    "R3_INCLUDE":"",
    "R3_SEQNUM":6,
    "R3_BOXED":"",
    "CATEGORY":"",
    "DIRECTION":"",
    "INSTANCE":"",
    "SYNCHRON":"",
    "KEYPARAM":"",
    "PROBLEMS":"",
    "WARNINGS":"",
    "PROBL_INF":"",
    "FURTHERDATA":"",
    "ENUMTYPE":""
   },
   {
    "OBJECT":"TABL",
    "OBJ_NAME":"ZBUSINESS_DOCUMENT_MESSAGE_HE3",
    "OBJECT1":"FIEL",
    "OBJ_NAME1":"RECIPIENT_PARTY",
    "OBJECT2":"FIEL",
    "OBJ_NAME2":"RECIPIENT_PARTY",
    "INACTIVE":"",
    "OBJECT_R":"TTYP",
    "OBJ_NAME_R":"ZBUSINESS_DOCUMENT_MESSAG_TAB1",
    "ID":"<element> RecipientParty <type> BusinessDocumentMessageHeader http://sap.com/xi/SD-BIL/Global2 http://sap.com/xi/SD-BIL/Global2",
    "IFR_TYPE":"element",
    "IFR_NAME":"RecipientParty",
    "IFR_TEXT":"",
    "IFR_LANGU":"",
    "IFR_REPTERM":"",
    "IFR_LABEL_F":"",
    "IFR_LABEL_C":"",
    "IFR_TEXTID":"",
    "IFR_TAGTYP":"L",
    "IFR_MINOCC":0,
    "IFR_MAXOCC":65535,
    "IFR_OPTNL":"X",
    "IFR_DEFLT":"",
    "IFR_QUALIF":"",
    "IFR_XSDTYP":"",
    "IFR_LENGTH":0,
    "IFR_MAXLEN":0,
    "IFR_MINLEN":0,
    "IFR_NILLABLE":"",
    "IFR_PATTRN":"",
    "IFR_PREC":0,
    "IFR_SCALE":-2,
    "IFR_FAULT":"",
    "IFR_ACTIONCODE":"",
    "IFR_IDEMPOTENT":"",
    "R3_TYPE":"FIEL",
    "R3_NAME":"RECIPIENT_PARTY",
    "R3_TEXT":"",
    "R3_DATATYP":"",
    "R3_LENGTH":0,
    "R3_DECIMAL":0,
    "R3_REFTO":"",
    "R3_DTREF":"",
    "R3_INCLUDE":"",
    "R3_SEQNUM":8,
    "R3_BOXED":"",
    "CATEGORY":"",
    "DIRECTION":"",
    "INSTANCE":"",
    "SYNCHRON":"",
    "KEYPARAM":"",
    "PROBLEMS":"",
    "WARNINGS":"",
    "PROBL_INF":"",
    "FURTHERDATA":"",
    "ENUMTYPE":""
   },
   {
    "OBJECT":"TABL",
    "OBJ_NAME":"ZBUSINESS_DOCUMENT_MESSAGE_HE3",
    "OBJECT1":"FIEL",
    "OBJ_NAME1":"RECONCILIATION_INDICATOR",
    "OBJECT2":"FIEL",
    "OBJ_NAME2":"RECONCILIATION_INDICATOR",
    "INACTIVE":"",
    "OBJECT_R":"DTEL",
    "OBJ_NAME_R":"ZINDICATOR2",
    "ID":"<element> ReconciliationIndicator <type> BusinessDocumentMessageHeader http://sap.com/xi/SD-BIL/Global2 http://sap.com/xi/SD-BIL/Global2",
    "IFR_TYPE":"element",
    "IFR_NAME":"ReconciliationIndicator",
    "IFR_TEXT":"",
    "IFR_LANGU":"",
    "IFR_REPTERM":"",
    "IFR_LABEL_F":"",
    "IFR_LABEL_C":"",
    "IFR_TEXTID":"",
    "IFR_TAGTYP":"E",
    "IFR_MINOCC":0,
    "IFR_MAXOCC":1,
    "IFR_OPTNL":"X",
    "IFR_DEFLT":"",
    "IFR_QUALIF":"",
    "IFR_XSDTYP":"",
    "IFR_LENGTH":0,
    "IFR_MAXLEN":0,
    "IFR_MINLEN":0,
    "IFR_NILLABLE":"",
    "IFR_PATTRN":"",
    "IFR_PREC":0,
    "IFR_SCALE":-2,
    "IFR_FAULT":"",
    "IFR_ACTIONCODE":"",
    "IFR_IDEMPOTENT":"",
    "R3_TYPE":"FIEL",
    "R3_NAME":"RECONCILIATION_INDICATOR",
    "R3_TEXT":"",
    "R3_DATATYP":"",
    "R3_LENGTH":0,
    "R3_DECIMAL":0,
    "R3_REFTO":"",
    "R3_DTREF":"",
    "R3_INCLUDE":"",
    "R3_SEQNUM":4,
    "R3_BOXED":"",
    "CATEGORY":"",
    "DIRECTION":"",
    "INSTANCE":"",
    "SYNCHRON":"",
    "KEYPARAM":"",
    "PROBLEMS":"",
    "WARNINGS":"",
    "PROBL_INF":"",
    "FURTHERDATA":"",
    "ENUMTYPE":""
   },
   {
    "OBJECT":"TABL",
    "OBJ_NAME":"ZBUSINESS_DOCUMENT_MESSAGE_HE3",
    "OBJECT1":"FIEL",
    "OBJ_NAME1":"REFERENCE_ID",
    "OBJECT2":"FIEL",
    "OBJ_NAME2":"REFERENCE_ID",
    "INACTIVE":"",
    "OBJECT_R":"TABL",
    "OBJ_NAME_R":"ZBUSINESS_DOCUMENT_MESSAGE_ID2",
    "ID":"<element> ReferenceID <type> BusinessDocumentMessageHeader http://sap.com/xi/SD-BIL/Global2 http://sap.com/xi/SD-BIL/Global2",
    "IFR_TYPE":"element",
    "IFR_NAME":"ReferenceID",
    "IFR_TEXT":"",
    "IFR_LANGU":"",
    "IFR_REPTERM":"",
    "IFR_LABEL_F":"",
    "IFR_LABEL_C":"",
    "IFR_TEXTID":"",
    "IFR_TAGTYP":"E",
    "IFR_MINOCC":0,
    "IFR_MAXOCC":1,
    "IFR_OPTNL":"X",
    "IFR_DEFLT":"",
    "IFR_QUALIF":"",
    "IFR_XSDTYP":"",
    "IFR_LENGTH":0,
    "IFR_MAXLEN":0,
    "IFR_MINLEN":0,
    "IFR_NILLABLE":"",
    "IFR_PATTRN":"",
    "IFR_PREC":0,
    "IFR_SCALE":-2,
    "IFR_FAULT":"",
    "IFR_ACTIONCODE":"",
    "IFR_IDEMPOTENT":"",
    "R3_TYPE":"FIEL",
    "R3_NAME":"REFERENCE_ID",
    "R3_TEXT":"",
    "R3_DATATYP":"",
    "R3_LENGTH":0,
    "R3_DECIMAL":0,
    "R3_REFTO":"",
    "R3_DTREF":"",
    "R3_INCLUDE":"",
    "R3_SEQNUM":2,
    "R3_BOXED":"",
    "CATEGORY":"",
    "DIRECTION":"",
    "INSTANCE":"",
    "SYNCHRON":"",
    "KEYPARAM":"",
    "PROBLEMS":"",
    "WARNINGS":"",
    "PROBL_INF":"",
    "FURTHERDATA":"",
    "ENUMTYPE":""
   },
   {
    "OBJECT":"TABL",
    "OBJ_NAME":"ZBUSINESS_DOCUMENT_MESSAGE_HE3",
    "OBJECT1":"FIEL",
    "OBJ_NAME1":"SENDER_BUSINESS_SYSTEM_ID",
    "OBJECT2":"FIEL",
    "OBJ_NAME2":"SENDER_BUSINESS_SYSTEM_ID",
    "INACTIVE":"",
    "OBJECT_R":"DTEL",
    "OBJ_NAME_R":"ZBUSINESS_SYSTEM_ID1",
    "ID":"<element> SenderBusinessSystemID <type> BusinessDocumentMessageHeader http://sap.com/xi/SD-BIL/Global2 http://sap.com/xi/SD-BIL/Global2",
    "IFR_TYPE":"element",
    "IFR_NAME":"SenderBusinessSystemID",
    "IFR_TEXT":"",
    "IFR_LANGU":"",
    "IFR_REPTERM":"",
    "IFR_LABEL_F":"",
    "IFR_LABEL_C":"",
    "IFR_TEXTID":"",
    "IFR_TAGTYP":"E",
    "IFR_MINOCC":0,
    "IFR_MAXOCC":1,
    "IFR_OPTNL":"X",
    "IFR_DEFLT":"",
    "IFR_QUALIF":"",
    "IFR_XSDTYP":"",
    "IFR_LENGTH":0,
    "IFR_MAXLEN":0,
    "IFR_MINLEN":0,
    "IFR_NILLABLE":"",
    "IFR_PATTRN":"",
    "IFR_PREC":0,
    "IFR_SCALE":-2,
    "IFR_FAULT":"",
    "IFR_ACTIONCODE":"",
    "IFR_IDEMPOTENT":"",
    "R3_TYPE":"FIEL",
    "R3_NAME":"SENDER_BUSINESS_SYSTEM_ID",
    "R3_TEXT":"",
    "R3_DATATYP":"",
    "R3_LENGTH":0,
    "R3_DECIMAL":0,
    "R3_REFTO":"",
    "R3_DTREF":"",
    "R3_INCLUDE":"",
    "R3_SEQNUM":5,
    "R3_BOXED":"",
    "CATEGORY":"",
    "DIRECTION":"",
    "INSTANCE":"",
    "SYNCHRON":"",
    "KEYPARAM":"",
    "PROBLEMS":"",
    "WARNINGS":"",
    "PROBL_INF":"",
    "FURTHERDATA":"",
    "ENUMTYPE":""
   },
   {
    "OBJECT":"TABL",
    "OBJ_NAME":"ZBUSINESS_DOCUMENT_MESSAGE_HE3",
    "OBJECT1":"FIEL",
    "OBJ_NAME1":"SENDER_PARTY",
    "OBJECT2":"FIEL",
    "OBJ_NAME2":"SENDER_PARTY",
    "INACTIVE":"",
    "OBJECT_R":"TABL",
    "OBJ_NAME_R":"ZBUSINESS_DOCUMENT_MESSAGE_HE4",
    "ID":"<element> SenderParty <type> BusinessDocumentMessageHeader http://sap.com/xi/SD-BIL/Global2 http://sap.com/xi/SD-BIL/Global2",
    "IFR_TYPE":"element",
    "IFR_NAME":"SenderParty",
    "IFR_TEXT":"",
    "IFR_LANGU":"",
    "IFR_REPTERM":"",
    "IFR_LABEL_F":"",
    "IFR_LABEL_C":"",
    "IFR_TEXTID":"",
    "IFR_TAGTYP":"E",
    "IFR_MINOCC":0,
    "IFR_MAXOCC":1,
    "IFR_OPTNL":"X",
    "IFR_DEFLT":"",
    "IFR_QUALIF":"",
    "IFR_XSDTYP":"",
    "IFR_LENGTH":0,
    "IFR_MAXLEN":0,
    "IFR_MINLEN":0,
    "IFR_NILLABLE":"",
    "IFR_PATTRN":"",
    "IFR_PREC":0,
    "IFR_SCALE":-2,
    "IFR_FAULT":"",
    "IFR_ACTIONCODE":"",
    "IFR_IDEMPOTENT":"",
    "R3_TYPE":"FIEL",
    "R3_NAME":"SENDER_PARTY",
    "R3_TEXT":"",
    "R3_DATATYP":"",
    "R3_LENGTH":0,
    "R3_DECIMAL":0,
    "R3_REFTO":"",
    "R3_DTREF":"",
    "R3_INCLUDE":"",
    "R3_SEQNUM":7,
    "R3_BOXED":"",
    "CATEGORY":"",
    "DIRECTION":"",
    "INSTANCE":"",
    "SYNCHRON":"",
    "KEYPARAM":"",
    "PROBLEMS":"",
    "WARNINGS":"",
    "PROBL_INF":"",
    "FURTHERDATA":"",
    "ENUMTYPE":""
   },
   {
    "OBJECT":"TABL",
    "OBJ_NAME":"ZBUSINESS_DOCUMENT_MESSAGE_HE3",
    "OBJECT1":"TABL",
    "OBJ_NAME1":"ZBUSINESS_DOCUMENT_MESSAGE_HE3",
    "OBJECT2":"TABL",
    "OBJ_NAME2":"ZBUSINESS_DOCUMENT_MESSAGE_HE3",
    "INACTIVE":"",
    "OBJECT_R":"",
    "OBJ_NAME_R":"",
    "ID":"<type> BusinessDocumentMessageHeader http://sap.com/xi/SD-BIL/Global2 http://sap.com/xi/SD-BIL/Global2",
    "IFR_TYPE":"type",
    "IFR_NAME":"BusinessDocumentMessageHeader",
    "IFR_TEXT":"",
    "IFR_LANGU":"",
    "IFR_REPTERM":"",
    "IFR_LABEL_F":"",
    "IFR_LABEL_C":"",
    "IFR_TEXTID":"",
    "IFR_TAGTYP":"",
    "IFR_MINOCC":0,
    "IFR_MAXOCC":0,
    "IFR_OPTNL":"",
    "IFR_DEFLT":"",
    "IFR_QUALIF":"",
    "IFR_XSDTYP":"",
    "IFR_LENGTH":0,
    "IFR_MAXLEN":0,
    "IFR_MINLEN":0,
    "IFR_NILLABLE":"",
    "IFR_PATTRN":"",
    "IFR_PREC":0,
    "IFR_SCALE":-2,
    "IFR_FAULT":"",
    "IFR_ACTIONCODE":"",
    "IFR_IDEMPOTENT":"",
    "R3_TYPE":"TABL",
    "R3_NAME":"ZBUSINESS_DOCUMENT_MESSAGE_HE3",
    "R3_TEXT":"Proxy Structure (generated)",
    "R3_DATATYP":"",
    "R3_LENGTH":0,
    "R3_DECIMAL":0,
    "R3_REFTO":"",
    "R3_DTREF":"",
    "R3_INCLUDE":"",
    "R3_SEQNUM":0,
    "R3_BOXED":"",
    "CATEGORY":"ifmtypedef",
    "DIRECTION":"",
    "INSTANCE":"",
    "SYNCHRON":"",
    "KEYPARAM":"",
    "PROBLEMS":"",
    "WARNINGS":"",
    "PROBL_INF":"",
    "FURTHERDATA":"",
    "ENUMTYPE":""
   }
  ]
 },
 {
  "table":"SPROXHDR",
  "data":
  [
   {
    "OBJECT":"TABL",
    "OBJ_NAME":"ZBUSINESS_DOCUMENT_MESSAGE_HE3",
    "INACTIVE":"",
    "OBJECT_M":"TABL",
    "OBJ_NAME_M":"ZBUSINESS_DOCUMENT_MESSAGE_HE3",
    "HASH_ID":"32F7595D935E1706D84086ECA26384599ACDAAF6",
    "ID":"<type> BusinessDocumentMessageHeader http://sap.com/xi/SD-BIL/Global2 http://sap.com/xi/SD-BIL/Global2",
    "IFR_GLOBAL":"X",
    "IFR_TYPE":"type",
    "IFR_NAME":"BusinessDocumentMessageHeader",
    "IFR_NSPCE":"http://sap.com/xi/SD-BIL/Global2",
    "IFR_GNSPCE":"http://sap.com/xi/SD-BIL/Global2",
    "CREATED_ON":"+020240508114349",
    "CREATED_BY":"SAP_CUSTOMER",
    "CHANGED_ON":"+020240508115752",
    "CHANGED_BY":"SAP_CUSTOMER",
    "GEN_VERS":5,
    "PREFIX":"",
    "CATEGORY":"ifmtypedef",
    "DIRECTION":"",
    "SYNCHRON":"",
    "GEN_APPL":"WEBSERVICES",
    "ENH_NAME":"",
    "ENH_NSPCE":"",
    "ENH_HASH_ID":"",
    "XML_NSPCE":"http://sap.com/xi/SD-BIL/Global2",
    "XML_NAME":"BusinessDocumentMessageHeader",
    "FURTHER_DATA":"",
    "BO_DATA":"",
    "CHANGED_ON_IFR":"0",
    "VERSION_ID":"",
    "IFR_STATE":"",
    "EVENT":"",
    "DYNAMIC":"",
    "STCM":"",
    "ABAP_LANGUAGE_VERSION":"5"
   }
  ]
 },
 {
  "table":"TADIR",
  "data":
  [
   {
    "PGMID":"R3TR",
    "OBJECT":"SPRX",
    "OBJ_NAME":"TABLZBUSINESS_DOCUMENT_MESSAGE_HE3",
    "KORRNUM":"",
    "SRCSYSTEM":"...",
    "AUTHOR":"SAP_CUSTOMER",
    "SRCDEP":"",
    "DEVCLASS":"ZETR_EXPORT",
    "GENFLAG":"",
    "EDTFLAG":"",
    "CPROJECT":" L",
    "MASTERLANG":"E",
    "VERSID":"",
    "PAKNOCHECK":"",
    "OBJSTABLTY":"",
    "COMPONENT":"",
    "CRELEASE":"",
    "DELFLAG":"",
    "TRANSLTTXT":"",
    "CREATED_ON":"2024-05-08",
    "CHECK_DATE":"2024-05-08",
    "CHECK_CFG":""
   }
  ]
 }
]