[
 {
  "table":"SRVDSRC",
  "data":
  [
   {
    "SRVDNAME":"ZETR_SD_EXP_HEAD",
    "VERSION":"A",
    "CHANGED_BY":"SAP_CUSTOMER",
    "CHANGED_ON":"2024-05-02",
    "CHANGED_AT":"20:55:01",
    "DT_UUID":"995523DB13041EEF8298C7BE14928029",
    "SOURCE_ORIGIN":"0",
    "SRVD_SOURCE_TYPE":"S",
    "ABAP_LANGUAGE_VERSION":"5"
   }
  ]
 },
 {
  "table":"SRVDSRCT",
  "data":
  [
   {
    "SRVDNAME":"ZETR_SD_EXP_HEAD",
    "VERSION":"A",
    "LANGUAGE":"E",
    "DESCRIPTION":"Export Header Service Desf."
   }
  ]
 },
 {
  "table":"SRVDSRC_SRC",
  "data":
  [
   {
    "SRVDNAME":"ZETR_SD_EXP_HEAD",
    "VERSION":"A",
    "SOURCE":"@EndUserText.label: 'Export Header Service Desf.'\r\ndefine service ZETR_SD_EXP_HEAD {\r\n  expose ZETR_DDL_C_EXP_HEADER as ExportHeader;\r\n  expose ZETR_DDL_C_EXP_INVH   as InvoiceHeader;\r\n  expose ZETR_DDL_C_EXP_INVI   as InvoiceItem;\r\n  expose ZETR_DDL_C_EXP_TXT    as ExportText;\r\n  expose ZETR_DDL_C_PRN_OPR    as PrintOperation;\r\n}"
   }
  ]
 },
 {
  "table":"SRVD_RT_ANNOS",
  "data":
  [
   {
    "SRVDNAME":"ZETR_SD_EXP_HEAD",
    "NAME":"ENDUSERTEXT.LABEL",
    "VALUE":"'Export Header Service Desf.'"
   }
  ]
 },
 {
  "table":"SRVD_RT_ANNOS_T",
  "data":
  [
   {
    "SRVDNAME":"ZETR_SD_EXP_HEAD",
    "LANGUAGE":"E",
    "NAME":"ENDUSERTEXT.LABEL",
    "TEXT":"Export Header Service Desf."
   }
  ]
 },
 {
  "table":"SRVD_RT_ENTITIES",
  "data":
  [
   {
    "SRVDNAME":"ZETR_SD_EXP_HEAD",
    "SERVICE":"ZETR_SD_EXP_HEAD",
    "EXPOSED_ARTIFACT":"ZETR_DDL_C_EXP_HEADER",
    "EXPOSED_ARTIFACT_TYPE":"E",
    "EXPOSED_ALIAS":"EXPORTHEADER",
    "EXPOSED_ALIAS_RAW":"ExportHeader",
    "INCL_SERVICE":""
   },
   {
    "SRVDNAME":"ZETR_SD_EXP_HEAD",
    "SERVICE":"ZETR_SD_EXP_HEAD",
    "EXPOSED_ARTIFACT":"ZETR_DDL_C_EXP_INVH",
    "EXPOSED_ARTIFACT_TYPE":"E",
    "EXPOSED_ALIAS":"INVOICEHEADER",
    "EXPOSED_ALIAS_RAW":"InvoiceHeader",
    "INCL_SERVICE":""
   },
   {
    "SRVDNAME":"ZETR_SD_EXP_HEAD",
    "SERVICE":"ZETR_SD_EXP_HEAD",
    "EXPOSED_ARTIFACT":"ZETR_DDL_C_EXP_INVI",
    "EXPOSED_ARTIFACT_TYPE":"E",
    "EXPOSED_ALIAS":"INVOICEITEM",
    "EXPOSED_ALIAS_RAW":"InvoiceItem",
    "INCL_SERVICE":""
   },
   {
    "SRVDNAME":"ZETR_SD_EXP_HEAD",
    "SERVICE":"ZETR_SD_EXP_HEAD",
    "EXPOSED_ARTIFACT":"ZETR_DDL_C_EXP_TXT",
    "EXPOSED_ARTIFACT_TYPE":"E",
    "EXPOSED_ALIAS":"EXPORTTEXT",
    "EXPOSED_ALIAS_RAW":"ExportText",
    "INCL_SERVICE":""
   },
   {
    "SRVDNAME":"ZETR_SD_EXP_HEAD",
    "SERVICE":"ZETR_SD_EXP_HEAD",
    "EXPOSED_ARTIFACT":"ZETR_DDL_C_PRN_OPR",
    "EXPOSED_ARTIFACT_TYPE":"E",
    "EXPOSED_ALIAS":"PRINTOPERATION",
    "EXPOSED_ALIAS_RAW":"PrintOperation",
    "INCL_SERVICE":""
   }
  ]
 },
 {
  "table":"SRVD_RT_HEADER",
  "data":
  [
   {
    "SRVDNAME":"ZETR_SD_EXP_HEAD",
    "SERVICE":"ZETR_SD_EXP_HEAD",
    "SERVICE_RAW":"ZETR_SD_EXP_HEAD",
    "SOURCE_TYPE":"S",
    "DT_UUID":"995523DB13041EEF8298C7BE14928029",
    "RT_HASH":"36123C67F633BE02A08F9DCE167031451A00F5E4",
    "GEN_VERSION":"0"
   }
  ]
 },
 {
  "table":"TADIR",
  "data":
  [
   {
    "PGMID":"R3TR",
    "OBJECT":"SRVD",
    "OBJ_NAME":"ZETR_SD_EXP_HEAD",
    "KORRNUM":"",
    "SRCSYSTEM":"...",
    "AUTHOR":"SAP_CUSTOMER",
    "SRCDEP":"",
    "DEVCLASS":"ZETR_EXPORT",
    "GENFLAG":"",
    "EDTFLAG":"",
    "CPROJECT":" L",
    "MASTERLANG":"E",
    "VERSID":"",
    "PAKNOCHECK":"",
    "OBJSTABLTY":"",
    "COMPONENT":"",
    "CRELEASE":"",
    "DELFLAG":"",
    "TRANSLTTXT":"",
    "CREATED_ON":"2023-12-14",
    "CHECK_DATE":"2023-12-14",
    "CHECK_CFG":""
   }
  ]
 }
]